{
    "name": "aurelia-custom-skeleton",
    "type": "project:application",
    "platform": {
        "id": "web",
        "displayName": "Web",
        "output": "scripts"
    },
    "run": {
        "basePath": "dist"
    },
    "transpiler": {
        "id": "typescript",
        "displayName": "TypeScript",
        "fileExtension": ".ts",
        "dtsSource": [
            "./typings/**/*.d.ts",
            "./typings_custom/**/*.d.ts"
        ],
        "source": "src/**/*.ts"
    },
    "markupProcessor": {
        "id": "none",
        "displayName": "None",
        "fileExtension": ".html",
        "source": "src/**/*.html"
    },
    "cssProcessor": {
        "id": "less",
        "displayName": "Less",
        "fileExtension": ".less",
        "source": "src/assets/less/template.less",
        "filename": "app.css"
    },
    "editor": {
        "id": "webstorm",
        "displayName": "WebStorm"
    },
    "unitTestRunner": {
        "id": "karma",
        "displayName": "Karma",
        "source": "test/unit/**/*.ts"
    },
    "minifyCss": {
        "output": "css",
        "sources": ["src/assets/css/base.css", "src/assets/css/app.css"],
        "filename": "styles.min.css"
    },
    "copyCss": {
        "output": "src/assets/css",
        "filename": "base.css",
        "sources": [
            "node_modules/font-awesome/css/*.min.css",
            "node_modules/bootstrap/dist/css/*.min.css",
            "node_modules/aurelia-editables/dist/css/*.css"
        ]
    },
    "copyFiles": [
        {
            "name": "copyFonts",
            "output": "fonts",
            "sources": [
                "node_modules/font-awesome/fonts/*",
                "node_modules/bootstrap/dist/fonts/*"
            ]
        }
    ],
    "dist": {
        "output": "dist",
        "sources": [
            "./css/**/*",
            "./data/**/*",
            "./fonts/**/*",
            "./locales/**/*",
            "./scripts/**/*",
            "./index.html"
        ]
    },
    "paths": {
        "root": "src",
        "resources": "src/resources",
        "elements": "src/resources/elements",
        "attributes": "src/resources/attributes",
        "valueConverters": "src/resources/value-converters",
        "bindingBehaviors": "src/resources/binding-behaviors"
    },
    "testFramework": {
        "id": "jasmine",
        "displayName": "Jasmine"
    },
    "build": {
        "targets": [
            {
                "id": "web",
                "displayName": "Web",
                "output": "scripts"
            }
        ],
        "loader": {
            "type": "require",
            "configTarget": "vendor-bundle.js",
            "includeBundleMetadataInConfig": "auto",
            "plugins": [
                {
                    "name": "text",
                    "extensions": [
                        ".html",
                        ".css"
                    ],
                    "stub": true
                }
            ]
        },
        "options": {
            "minify": "stage & prod",
            "sourcemaps": "dev & stage"
        },
        "bundles": [
            {
                "name": "app-bundle.js",
                "source": [
                    "[**/*.js]",
                    "**/*.{css,html}"
                ]
            },
            {
                "name": "vendor-bundle.js",
                "prepend": [
                    "node_modules/bluebird/js/browser/bluebird.core.js",
                    "node_modules/interact.js/dist/interact.min.js",
                    "scripts/require.js"
                ],
                "dependencies": [
                    "aurelia-binding",
                    "aurelia-bootstrapper",
                    "aurelia-dependency-injection",
                    "aurelia-event-aggregator",
                    "aurelia-framework",
                    "aurelia-history",
                    "aurelia-history-browser",
                    "aurelia-http-client",
                    "aurelia-loader",
                    "aurelia-loader-default",
                    "aurelia-logging",
                    "aurelia-logging-console",
                    "aurelia-metadata",
                    "aurelia-pal",
                    "aurelia-pal-browser",
                    "aurelia-path",
                    "aurelia-polyfills",
                    "aurelia-route-recognizer",
                    "aurelia-router",
                    "aurelia-task-queue",
                    "aurelia-templating",
                    "aurelia-templating-binding",
                    {
                        "name": "text",
                        "path": "../scripts/text"
                    },
                    {
                        "name": "aurelia-templating-resources",
                        "path": "../node_modules/aurelia-templating-resources/dist/amd",
                        "main": "aurelia-templating-resources"
                    },
                    {
                        "name": "aurelia-templating-router",
                        "path": "../node_modules/aurelia-templating-router/dist/amd",
                        "main": "aurelia-templating-router"
                    },
                    {
                        "name": "aurelia-testing",
                        "path": "../node_modules/aurelia-testing/dist/amd",
                        "main": "aurelia-testing",
                        "env": "dev"
                    },
                    {
                        "name": "aurelia-validation",
                        "path": "../node_modules/aurelia-validation/dist/amd",
                        "main": "aurelia-validation"
                    },
                    {
                        "name": "i18next",
                        "path": "../node_modules/i18next/dist/umd",
                        "main": "i18next"
                    },
                    {
                        "name": "aurelia-i18n",
                        "path": "../node_modules/aurelia-i18n/dist/amd",
                        "main": "aurelia-i18n"
                    },
                    {
                        "name": "i18next-xhr-backend",
                        "path": "../node_modules/i18next-xhr-backend/dist/umd",
                        "main": "i18nextXHRBackend"
                    },
                    "lodash",
                    {
                        "name": "jquery",
                        "path": "../node_modules/jquery/dist",
                        "main": "jquery.min"
                    },
                    {
                        "name": "bootstrap",
                        "path": "../node_modules/bootstrap/dist",
                        "main": "js/bootstrap.min",
                        "deps": ["jquery"],
                        "exports": "$"
                    },
                    "moment",
                    {
                        "name": "aurelia-editables",
                        "path": "../node_modules/aurelia-editables/dist/amd",
                        "main": "aurelia-editables",
                        "resources": ["**/*.html"]
                    }
                ]
            }
        ]
    }
}
